odoo/addons/product_replenishment_cost/README.rst
odoo/addons/product_replenishment_cost/__init__.py
odoo/addons/product_replenishment_cost/__manifest__.py
odoo/addons/product_replenishment_cost/i18n/es.po
odoo/addons/product_replenishment_cost/i18n/fr.po
odoo/addons/product_replenishment_cost/i18n/it.po
odoo/addons/product_replenishment_cost/i18n/nl.po
odoo/addons/product_replenishment_cost/i18n/product_replenishment_cost.pot
odoo/addons/product_replenishment_cost/i18n/pt.po
odoo/addons/product_replenishment_cost/i18n/pt_BR.po
odoo/addons/product_replenishment_cost/i18n/zh_CN.po
odoo/addons/product_replenishment_cost/models/__init__.py
odoo/addons/product_replenishment_cost/models/product_product.py
odoo/addons/product_replenishment_cost/readme/CONTRIBUTORS.rst
odoo/addons/product_replenishment_cost/readme/DESCRIPTION.rst
odoo/addons/product_replenishment_cost/readme/ROADMAP.rst
odoo/addons/product_replenishment_cost/static/description/icon.png
odoo/addons/product_replenishment_cost/static/description/index.html
odoo/addons/product_replenishment_cost/tests/__init__.py
odoo/addons/product_replenishment_cost/tests/test_module.py
odoo/addons/product_replenishment_cost/views/product_view.xml
odoo_addon_product_replenishment_cost-16.0.1.0.0.9.dist-info/METADATA
odoo_addon_product_replenishment_cost-16.0.1.0.0.9.dist-info/WHEEL
odoo_addon_product_replenishment_cost-16.0.1.0.0.9.dist-info/top_level.txt
odoo_addon_product_replenishment_cost-16.0.1.0.0.9.dist-info/RECORD
